nameko_autocrud/__init__.py
nameko_autocrud/managers.py
nameko_autocrud/serializers.py
nameko_autocrud/storage.py
nameko_autocrud-0.2.0.dist-info/METADATA
nameko_autocrud-0.2.0.dist-info/RECORD
nameko_autocrud-0.2.0.dist-info/WHEEL
nameko_autocrud-0.2.0.dist-info/top_level.txt
nameko_autocrud-0.2.0.dist-info/zip-safe
