Metadata-Version: 2.1
Name: nameko-autocrud
Version: 0.2.0
Summary: Autocrud utility for nameko services
Home-page: http://github.com/timbu/nameko-autocrud
Author: timbu
License: Apache License, Version 2.0
Platform: UNKNOWN
Classifier: Programming Language :: Python
Classifier: Operating System :: MacOS :: MacOS X
Classifier: Operating System :: POSIX
Classifier: Programming Language :: Python :: 2
Classifier: Programming Language :: Python :: 2.7
Classifier: Programming Language :: Python :: 3
Classifier: Programming Language :: Python :: 3.3
Classifier: Programming Language :: Python :: 3.4
Classifier: Topic :: Internet
Classifier: Topic :: Software Development :: Libraries :: Python Modules
Classifier: Intended Audience :: Developers
Provides-Extra: dev
Requires-Dist: nameko (>=2.6.0)
Requires-Dist: sqlalchemy (>=1.0.16)
Requires-Dist: sqlalchemy-filters (>=0.4.0)
Requires-Dist: python-dateutil (>=2.6.1)
Requires-Dist: sqlalchemy-utils (>=0.32.5)
Provides-Extra: dev
Requires-Dist: coverage (==4.0.3); extra == 'dev'
Requires-Dist: flake8 (==2.5.4); extra == 'dev'
Requires-Dist: pylint (==1.5.5); extra == 'dev'
Requires-Dist: pytest (==3.0.5); extra == 'dev'
Requires-Dist: nameko-sqlalchemy (>=0.1.0); extra == 'dev'
